Metadata-Version: 1.0
Name: rdfunniest
Version: 0.1.1
Summary: The funniest joke in the world
Home-page: UNKNOWN
Author: Roman Dmytriv
Author-email: dmytrivdev@gmail.com
License: MIT
Platform: UNKNOWN
